<?xml version="1.0" encoding="utf-8"?>
<robot xmlns:xsi="http://www.w3.org/2001/XMLSchema-instance" xsi:noNamespaceSchemaLocation="moves.xsd">
  <constants>
    <!--konstanty sem-->
  </constants>
  <low_skills>
    <low_skill name="turnleft90_faster" firstPhase="turnleft90_faster_Phase0">
		<type>rotation</type>
		<author>Androids</author>
		<extendedFromMove></extendedFromMove>
		<description>Player turns 90 degrees to the left. Move is stable but relatively slow.</description>
	</low_skill>
  </low_skills>

    <phases>
    <phase name="turnleft90_faster_Phase0" next="turnleft90_faster_Phase1">
      <effectors>
		<he1 end="0" />
		<he2 end="0" />
		<rae2 end="0" />
		<lae2 end="0" />
		<rle1 end="0" />
		<lle1 end="0" />
		<rle2 end="0" />
		<lle2 end="0" />
		<lle6 end="0" />
        <lle4 end="-20" />
        <rle4 end="-40" />
        <lle3 end="20" />
        <rle6 end="-10" />
        <lle5 end="20" />
        <rle5 end="20" />
        <rle3 end="40" />
        <rae3 end="90" />
        <lae1 end="-120" />
        <rae1 end="-120" />
        <lae4 end="-90" />
        <rae4 end="90" />
        <lae3 end="-90" />
      </effectors>
      <duration>600</duration>
    </phase>
    <phase name="turnleft90_faster_Phase1" next="turnleft90_faster_Phase2">
      <effectors>
        <rle1 end="-45" />
        <rle2 end="5" />
        <rle3 end="20" />
        <rle6 end="-15" />
        <rle5 end="25" />
        <lle1 end="-30" />
      </effectors>
      <duration>300</duration>
    </phase>
    <phase name="turnleft90_faster_Phase2" next="turnleft90_faster_Phase3">
      <effectors>
        <lle3 end="-10" />
        <lle2 end="15" />
        <lle4 end="-50" />
        <lle1 end="-90" />
      </effectors>
      <duration>300</duration>
    </phase>
    <phase name="turnleft90_faster_Phase3" next="turnleft90_faster_Phase4">
      <effectors>
        <lle3 end="-25" />
        <lle2 end="5" />
        <rle2 end="15" />
        <lle4 end="-40" />
        <rle5 end="20" />
        <rle1 end="-55" />
      </effectors>
      <duration>300</duration>
    </phase>
    <phase name="turnleft90_faster_Phase4" next="turnleft90_faster_Phase5">
      <effectors>
        <rle5 end="10" />
        <lle5 end="25" />
        <rle3 end="10" />
        <rle4 end="-30" />
      </effectors>
      <duration>300</duration>
    </phase>
    <phase name="turnleft90_faster_Phase5" next="turnleft90_faster_Phase6">
      <effectors>
        <lle6 end="15" />
        <rle6 end="-5" />
        <rle1 end="-50" />
        <rle5 end="-5" />
        <lle5 end="35" />
        <lle4 end="-45" />
      </effectors>
      <duration>300</duration>
    </phase>
    <phase name="turnleft90_faster_Phase6" next="turnleft90_faster_Phase7">
      <effectors>
        <lle3 end="-5" />
        <lle1 end="0" />
        <rle5 end="16" />
        <lle5 end="30" />
        <rle1 end="0" />
        <lle3 end="20" />
        <rle3 end="40" />
      </effectors>
      <duration>600</duration>
    </phase>
    <phase name="turnleft90_faster_Phase7" isFinal="true">
      <effectors>
        <lle2 end="0" />
        <rle5 end="10" />
        <lle5 end="10" />
        <rle4 end="-20" />
        <rle6 end="0" />
        <lle6 end="0" />
        <lle1 end="0" />
        <rle2 end="0" />
        <lle4 end="-20" />
        <rle3 end="20" />
      </effectors>
      <duration>600</duration>
      <finalize>straighten</finalize>
    </phase>
  </phases>
</robot>